nojsoncomments.cpython-310-darwin.so
nojsoncomments-0.3.dist-info/LICENSE
nojsoncomments-0.3.dist-info/METADATA
nojsoncomments-0.3.dist-info/WHEEL
nojsoncomments-0.3.dist-info/top_level.txt
nojsoncomments-0.3.dist-info/RECORD
